m3learning_util-2.0.10.dist-info/licenses/LICENSE.txt
m3util/__init__.py
m3util/converters/__init__.py
m3util/converters/complex.py
m3util/datafed/datafed.py
m3util/globus/__init__.py
m3util/globus/globus.py
m3util/info/computer.py
m3util/ml/__init__.py
m3util/ml/inference.py
m3util/ml/logging.py
m3util/ml/preprocessor.py
m3util/ml/rand.py
m3util/ml/regularization.py
m3util/ml/optimizers/AdaHessian.py
m3util/ml/optimizers/TrustRegion.py
m3util/ml/optimizers/__init__.py
m3util/notebooks/__init__.py
m3util/notebooks/checksum.py
m3util/notebooks/skip_execution.py
m3util/notebooks/slides.py
m3util/pandas/__init__.py
m3util/pandas/filter.py
m3util/util/IO.py
m3util/util/__init__.py
m3util/util/code.py
m3util/util/generate_init.py
m3util/util/h5.py
m3util/util/hashing.py
m3util/util/kwargs.py
m3util/util/search.py
m3util/viz/__init__.py
m3util/viz/arrows.py
m3util/viz/colorbars.py
m3util/viz/images.py
m3util/viz/layout.py
m3util/viz/lines.py
m3util/viz/movies.py
m3util/viz/positioning.py
m3util/viz/printing.py
m3util/viz/style.py
m3util/viz/text.py
m3learning_util-2.0.10.dist-info/METADATA
m3learning_util-2.0.10.dist-info/WHEEL
m3learning_util-2.0.10.dist-info/entry_points.txt
m3learning_util-2.0.10.dist-info/top_level.txt
m3learning_util-2.0.10.dist-info/RECORD
