Metadata-Version: 2.4
Name: M3Learning-Util
Version: 2.0.10
Summary: Add a short description here!
Home-page: https://m3-learning.com
Author: Joshua C. Agar
Author-email: jca92@drexel.edu
License: MIT
Project-URL: Documentation, https://pyscaffold.org/
Platform: any
Classifier: Development Status :: 4 - Beta
Classifier: Programming Language :: Python
Requires-Python: >=3.11
License-File: LICENSE.txt
Requires-Dist: importlib-metadata; python_version < "3.8"
Requires-Dist: numpy
Requires-Dist: pygments
Requires-Dist: wget
Requires-Dist: h5py
Requires-Dist: torch
Requires-Dist: matplotlib
Requires-Dist: opencv-python
Requires-Dist: tqdm
Requires-Dist: seaborn
Requires-Dist: requests
Requires-Dist: globus-cli
Requires-Dist: datafed
Requires-Dist: tensorflow
Requires-Dist: pytest
Provides-Extra: testing
Requires-Dist: setuptools; extra == "testing"
Requires-Dist: pytest; extra == "testing"
Requires-Dist: pytest-cov; extra == "testing"
Dynamic: license-file
